strangeworks_qaoa/__init__.py
strangeworks_qaoa/sdk.py
strangeworks_qaoa/serializer.py
strangeworks_qaoa/utils.py
strangeworks_qaoa-0.1.13.dist-info/METADATA
strangeworks_qaoa-0.1.13.dist-info/WHEEL
strangeworks_qaoa-0.1.13.dist-info/licenses/LICENSE
strangeworks_qaoa-0.1.13.dist-info/RECORD
