Metadata-Version: 2.4
Name: strangeworks-qaoa
Version: 0.1.13
Summary: Extension to strangeworks sdk to allow user to run qaoa service
License-File: LICENSE
Author: SFlann
Author-email: stuart@strangeworks.com
Requires-Python: >=3.10,<4.0
Classifier: Programming Language :: Python :: 3
Classifier: Programming Language :: Python :: 3.10
Classifier: Programming Language :: Python :: 3.11
Classifier: Programming Language :: Python :: 3.12
Classifier: Programming Language :: Python :: 3.13
Classifier: Programming Language :: Python :: 3.14
Requires-Dist: dimod (>=0.12.4,<0.13.0)
Requires-Dist: networkx (>=3.0,<4.0)
Requires-Dist: numpy (==1.23.5)
Requires-Dist: strangeworks (>=0.6.1,<0.7.0)
